[ {"citation" : "Seuls ceux qui sont suffisamment fous pour penser qu'ils peuvent changer le monde y arrivent.",
 "auteur" : "Steve Jobs" },
 
{"citation" : "L'homme est bon, mais le veau est meilleur.", "auteur" : "Bertolt Brecht"},

{"citation" : "Entre la crainte et l'intérêt, la Liberté de l'Homme ne réside que dans ses choix.", "auteur" : "Auteurs divers homme"},

{"citation" : "Celui qui sait s'arrêter ne périclite jamais. Il pourra subsister longtemps.", "auteur" : "La Rochefoucauld "},

{"citation" : "Voulez-vous compter vos amis ? Empruntez-leur de l'argent.", "auteur" : "Alexandre Dumas fils"},



{ "citation" :"Et c'est bien là le génie : l'intelligence qui connaît ses frontières.", "auteur" : "Albert Camus"},

{"citation" : "N'importe quel type intelligent peut faire les choses plus compliquées. Mais il faut du génie pour faire plus simple.", "auteur" : "Albert Einstein"}, 

{"citation" :  "La femme a l'orgueil de vouloir être toujours au premier plan dans la vie de son mari." , "auteur" : "Alexandre Dumas fils"},

{ "citation" : "Une femme est comme votre ombre, courez après, elle vous fuit ; fuyez-la, elle vous court après !", "auteur" : "Alfred de Musset "},

{ "citation" : "En art comme en amour, l'instinct suffit.", "auteur" : "Anatole France"},


{ "citation" : "Le cerveau ne s'use que si l'on ne s'en sert pas", "auteur" : "Bernard Werber"},

{ "citation" : "La compétence sans autorité est aussi impuissante que l'autorité sans compétence.", "auteur" : "Gustave Le Bon"},

{ "citation" : "L'homme n'a pas besoin que de pain, il a aussi besoin de considération", "auteur" : "Ralph Waldo Emerson"},

{ "citation" : "Plus on impose des contraintes, plus on se libère. Et l'arbitraire de la contrainte ne sert qu'à obtenir une précision d'exécution.", "auteur" : "Igor Stravinsky"},

{ "citation" : "Je ne crois pas qu'avoir étudié soit une si grande chose si l'on n'étudie plus", "auteur" : "Alain "}


]